<?xml version="1.0" encoding="utf-8" ?><dwsync><file name="kickoff.js" server="www.icontel.cl//www/" local="0" remote="0" Dst="-1" /><file name="kickoff.js" server="www.icontel.cl//www/intranet/" local="0" remote="0" Dst="-1" /><file name="kickoff.js" server="ftp.icontel.cl//www/intranet/" local="3846404609" remote="3847873920" Dst="-1" /><file name="sort_column.js" server="ftp.icontel.cl//www/intranet/" local="0" remote="0" Dst="-1" /><file name="kickoff.js" server="ftp.icontel.cl//www/" local="0" remote="0" Dst="-1" /><file name="sort_column.js" server="ftp.icontel.cl//www/" local="0" remote="0" Dst="-1" /><file name="kickoff.js" server="172.16.10.15//intranet/" local="0" remote="0" Dst="-1" /><file name="cm_cobranza_comercial.js" server="ftp.icontel.cl//www/intranet/" local="3847875996" remote="3847875960" Dst="-1" /><file name="cm_tareas_pendientes.js" server="ftp.icontel.cl//www/intranet/" local="3847279845" remote="3847873920" Dst="-1" /><file name="cm_sort.js" server="ftp.icontel.cl//www/intranet/" local="3847212108" remote="3847873920" Dst="-1" /><file name="cm_cobranza_comercial_v2.js" server="ftp.icontel.cl//www/intranet/" local="3847484730" remote="3847876320" Dst="-1" /></dwsync>